setup.cfg
setup.py
aiohipchat/__init__.py
aiohipchat.egg-info/PKG-INFO
aiohipchat.egg-info/SOURCES.txt
aiohipchat.egg-info/dependency_links.txt
aiohipchat.egg-info/requires.txt
aiohipchat.egg-info/top_level.txt